yuewen/__init__.py
yuewen/open.py
yuewen/quick_spread.py
yuewen/wechat_activity.py
yuewen/wechat_spread.py
yuewen/yuewen.py
yuewen-0.0.38.dist-info/METADATA
yuewen-0.0.38.dist-info/WHEEL
yuewen-0.0.38.dist-info/top_level.txt
yuewen-0.0.38.dist-info/RECORD
