Metadata-Version: 2.4
Name: yuewen
Version: 0.0.38
Summary: 阅文小说平台的方法封装
Home-page: https://gitee.com/ZeroSeeker/yuewen
Author: ZeroSeeker
Author-email: zeroseeker@foxmail.com
Classifier: Programming Language :: Python :: 3
Classifier: License :: OSI Approved :: MIT License
Classifier: Operating System :: OS Independent
Requires-Dist: requests>=2.27.1
Requires-Dist: showlog==0.0.6
Requires-Dist: lazysdk>=0.0.21
Dynamic: author
Dynamic: author-email
Dynamic: classifier
Dynamic: description
Dynamic: description-content-type
Dynamic: home-page
Dynamic: requires-dist
Dynamic: summary
